dofutils/__init__.py
dofutils/encoding/__init__.py
dofutils/encoding/base64.py
dofutils/encoding/checksum.py
dofutils/encoding/key.py
dofutils/encoding/password_encoder.py
dofutils/encoding/xor_cipher.py
dofutils/maps/__init__.py
dofutils/maps/constant/__init__.py
dofutils/maps/constant/cell_movement.py
dofutils/maps/constant/direction.py
dofutils/value/__init__.py
dofutils/value/color.py
dofutils/value/constant/__init__.py
dofutils/value/constant/gender.py
dofutils/value/constant/race.py
dofutils/value/dimension.py
dofutils/value/interval.py
dofutils-0.0.4.dist-info/entry_points.txt
dofutils-0.0.4.dist-info/WHEEL
dofutils-0.0.4.dist-info/METADATA
dofutils-0.0.4.dist-info/RECORD
