Metadata-Version: 2.1
Name: dofutils
Version: 0.0.4
Summary: Collection of useful things to build Dofus Retro bot or emulator
Home-page: https://github.com/Dysta/Dofutils
Keywords: dofus retro,dofus,retro,bot,emulateur
Author: Dysta
Requires-Python: >=3.8
Classifier: Development Status :: 3 - Alpha
Classifier: Programming Language :: Python :: 3
Classifier: Programming Language :: Python :: 3.10
Classifier: Programming Language :: Python :: 3.8
Classifier: Programming Language :: Python :: 3.9
Requires-Dist: black (>=21.9b0,<22.0)
Requires-Dist: mypy (>=0.910,<0.911)
Project-URL: Repository, https://github.com/Dysta/Dofutils
